qnxmount/__init__.py
qnxmount/__main__.py
qnxmount/bug.py
qnxmount/efs/__init__.py
qnxmount/efs/interface.py
qnxmount/efs/mount.py
qnxmount/efs/parser.ksy
qnxmount/efs/parser.py
qnxmount/etfs/__init__.py
qnxmount/etfs/interface.py
qnxmount/etfs/mount.py
qnxmount/etfs/parser.ksy
qnxmount/etfs/parser.py
qnxmount/logger.py
qnxmount/qnx6/__init__.py
qnxmount/qnx6/interface.py
qnxmount/qnx6/mount.py
qnxmount/qnx6/parser.ksy
qnxmount/qnx6/parser.py
qnxmount/stream.py
qnxmount-0.1.9.dist-info/LICENSE
qnxmount-0.1.9.dist-info/METADATA
qnxmount-0.1.9.dist-info/WHEEL
qnxmount-0.1.9.dist-info/RECORD
