Metadata-Version: 2.3
Name: qnxmount
Version: 0.1.9
Summary: read only mounters for qnx filesystems
License: Apache-2.0
Author: Francis Hoogendijk
Author-email: f.hoogendijk@nfi.nl
Requires-Python: >=3.7,<4.0
Classifier: License :: OSI Approved :: Apache Software License
Classifier: Programming Language :: Python :: 3
Classifier: Programming Language :: Python :: 3.7
Classifier: Programming Language :: Python :: 3.8
Classifier: Programming Language :: Python :: 3.9
Classifier: Programming Language :: Python :: 3.10
Classifier: Programming Language :: Python :: 3.11
Classifier: Programming Language :: Python :: 3.12
Classifier: Programming Language :: Python :: 3.13
Requires-Dist: crcmod (>=1.7,<2.0)
Requires-Dist: fusepy (>=3.0.1,<4.0.0)
Requires-Dist: kaitaistruct (>=0.10,<0.11)
Project-URL: Repository, https://github.com/NetherlandsForensicInstitute/qnxmount
